admin_list_charts/__init__.py
admin_list_charts/admin.py
admin_list_charts/apps.py
admin_list_charts/static/admin_list_charts/css/chart.min.css
admin_list_charts/static/admin_list_charts/js/chart.bundle.min.js
admin_list_charts/templates/admin_list_charts/change_list_with_chart.html
django_admin_list_charts-0.1.3.dist-info/LICENSE
django_admin_list_charts-0.1.3.dist-info/METADATA
django_admin_list_charts-0.1.3.dist-info/WHEEL
django_admin_list_charts-0.1.3.dist-info/top_level.txt
django_admin_list_charts-0.1.3.dist-info/RECORD
